handy_nn/__init__.py
handy_nn/losses.py
handy_nn/py.typed
handy_nn-0.0.6.dist-info/licenses/LICENSE
handy_nn-0.0.6.dist-info/METADATA
handy_nn-0.0.6.dist-info/WHEEL
handy_nn-0.0.6.dist-info/top_level.txt
handy_nn-0.0.6.dist-info/RECORD
