Metadata-Version: 2.4
Name: handy-nn
Version: 0.0.6
Summary: Delightful and useful neural networks models, including OrdinalRegressionLoss, etc.
Author-email: Kael Zhang <i+pypi@kael.me>
License-Expression: MIT
Project-URL: Homepage, https://github.com/kaelzhang/handy-nn
Keywords: neural-networks,pytorch,machine-learning,ordinal-regression,models
Classifier: Topic :: Software Development :: Libraries :: Python Modules
Classifier: Programming Language :: Python :: 3
Classifier: Programming Language :: Python :: 3.7
Classifier: Programming Language :: Python :: 3.8
Classifier: Programming Language :: Python :: 3.9
Classifier: Programming Language :: Python :: 3.10
Classifier: Programming Language :: Python :: 3.11
Classifier: Programming Language :: Python :: 3.12
Classifier: Programming Language :: Python :: Implementation :: PyPy
Classifier: Topic :: Software Development :: Libraries :: Python Modules
Requires-Python: >=3.7
License-File: LICENSE
Requires-Dist: torch
Provides-Extra: dev
Requires-Dist: codecov; extra == "dev"
Requires-Dist: coverage; extra == "dev"
Requires-Dist: ruff; extra == "dev"
Requires-Dist: pytest; extra == "dev"
Requires-Dist: pytest-cov; extra == "dev"
Requires-Dist: twine; extra == "dev"
Requires-Dist: mypy; extra == "dev"
Requires-Dist: build; extra == "dev"
Dynamic: license-file
